log_essence/__init__.py
log_essence/_version.py
log_essence/cli.py
log_essence/config.py
log_essence/py.typed
log_essence/redaction.py
log_essence/server.py
log_essence/demo/__init__.py
log_essence/demo/cli.py
log_essence/demo/compose.py
log_essence/demo/runner.py
log_essence/demo/schema.py
log_essence/demo/tts.py
log_essence/ui/__init__.py
log_essence/ui/app.py
log_essence/ui/models.py
log_essence-0.1.0b3.dist-info/METADATA
log_essence-0.1.0b3.dist-info/WHEEL
log_essence-0.1.0b3.dist-info/entry_points.txt
log_essence-0.1.0b3.dist-info/licenses/LICENSE
log_essence-0.1.0b3.dist-info/RECORD
