Metadata-Version: 2.4
Name: log-essence
Version: 0.1.0b3
Summary: Intelligent log analysis for LLMs - extract patterns, redact secrets, compress 50%+
Project-URL: Homepage, https://github.com/petebytes/log-essence
Project-URL: Repository, https://github.com/petebytes/log-essence
Project-URL: Issues, https://github.com/petebytes/log-essence/issues
Author: Pete
License-Expression: MIT
License-File: LICENSE
Keywords: ai,claude,devtools,docker-logs,drain3,llm,log-analysis,log-parser,logs,mcp,observability,pii-redaction,secret-detection,semantic-clustering,template-extraction
Classifier: Development Status :: 4 - Beta
Classifier: Environment :: Console
Classifier: Intended Audience :: Developers
Classifier: License :: OSI Approved :: MIT License
Classifier: Operating System :: OS Independent
Classifier: Programming Language :: Python :: 3
Classifier: Programming Language :: Python :: 3.11
Classifier: Programming Language :: Python :: 3.12
Classifier: Programming Language :: Python :: 3.13
Classifier: Topic :: Software Development :: Libraries :: Python Modules
Classifier: Topic :: System :: Logging
Classifier: Typing :: Typed
Requires-Python: >=3.11
Requires-Dist: drain3>=0.9.11
Requires-Dist: fastembed>=0.4.0
Requires-Dist: fastmcp>=0.4.0
Requires-Dist: numpy>=1.26.0
Requires-Dist: pyyaml>=6.0
Requires-Dist: tiktoken>=0.7.0
Provides-Extra: demo
Requires-Dist: httpx>=0.27.0; extra == 'demo'
Requires-Dist: playwright>=1.40.0; extra == 'demo'
Requires-Dist: python-dotenv>=1.0.0; extra == 'demo'
Provides-Extra: ui
Requires-Dist: streamlit>=1.40.0; extra == 'ui'
